foamquant/Average.py
foamquant/Figure.py
foamquant/FromBinary.py
foamquant/FromContact.py
foamquant/FromLabelled.py
foamquant/Helper.py
foamquant/Movie.py
foamquant/Passage.py
foamquant/Process.py
foamquant/Shape.py
foamquant/Texture.py
foamquant/Tracking.py
foamquant/VTK.py
foamquant/__init__.py
foamquant-0.1.0.dist-info/LICENCE
foamquant-0.1.0.dist-info/METADATA
foamquant-0.1.0.dist-info/WHEEL
foamquant-0.1.0.dist-info/top_level.txt
foamquant-0.1.0.dist-info/RECORD
